[
  {
    "id": "C-BwpSqaO5NLIJDhYHjSx",
    "title": "Backend Developer",
    "companyId": "pVbRRBQtMVw6lUAkj1k43",
    "description": "Backend"
  },
  {
    "id": "UZhjQJIZ5ryeMIa7FBd58",
    "title": "Full-Stack Developer",
    "companyId": "pVbRRBQtMVw6lUAkj1k43",
    "description": "Full stack\n"
  },
  {
    "id": "sERrRizhlfTbva0HLSzIk",
    "title": "DevOps Engineer",
    "description": "DevOps things",
    "companyId": "pVbRRBQtMVw6lUAkj1k43"
  },
  {
    "id": "oecP5-tjdMnbNPe7GQU1h",
    "title": "Designer",
    "description": "Lorem Ipsum",
    "companyId": "pVbRRBQtMVw6lUAkj1k43"
  },
  {
    "id": "fo9-KESw7f11Qs_a2Hu4p",
    "title": "Frontend Developer",
    "companyId": "pVbRRBQtMVw6lUAkj1k43",
    "description": ""
  }
]
